preoccupied/proxytype/__init__.py
preoccupied/proxytype/mypy.py
preoccupied/proxytype/py.typed
preoccupied.proxytype-0.4.0.dist-info/LICENSE
preoccupied.proxytype-0.4.0.dist-info/METADATA
preoccupied.proxytype-0.4.0.dist-info/WHEEL
preoccupied.proxytype-0.4.0.dist-info/top_level.txt
preoccupied.proxytype-0.4.0.dist-info/RECORD
