Metadata-Version: 2.1
Name: preoccupied.proxytype
Version: 0.4.0
Summary: static typing support for dynamic proxy classes
Home-page: https://github.com/obriencj/python-proxytype
Author: Christopher O'Brien
Author-email: obriencj@preoccupied.net
License: GNU General Public License v3 (GPLv3)
Project-URL: Source, https://github.com/obriencj/python-proxytype
Project-URL: Issues, https://github.com/obriencj/python-proxytype/issues
Platform: any
Classifier: Development Status :: 4 - Beta
Classifier: Environment :: Console
Classifier: Intended Audience :: Developers
Classifier: License :: OSI Approved :: GNU General Public License v3 (GPLv3)
Classifier: Natural Language :: English
Classifier: Programming Language :: Python :: 3
Classifier: Programming Language :: Python :: 3.6
Classifier: Programming Language :: Python :: 3.7
Classifier: Programming Language :: Python :: 3.8
Classifier: Programming Language :: Python :: 3.9
Classifier: Programming Language :: Python :: 3.10
Classifier: Programming Language :: Python :: 3.11
Classifier: Topic :: Software Development :: Build Tools
Classifier: Topic :: Utilities
License-File: LICENSE
